[
  {
    "conference": [
      {
        "id": "bf55ded2-ffe4-4705-8c08-9cffa6b8f540",
        "title": "International Conference on Sustainable Development",
        "start_time": "2023-09-15T02:36:58.682Z",
        "end_time": "2023-09-14T18:19:47.742Z",
        "created_at": "2023-09-14T19:09:29.346Z",
        "updated_at": "2023-09-15T04:46:49.011Z",
        "organization_id": "main_entity_pk"
      },
      {
        "id": "ee58effc-7aa3-4732-8d0f-c7ccd1f6a22f",
        "title": "Annual AI Summit",
        "start_time": "2023-09-15T07:22:53.048Z",
        "end_time": "2023-09-14T15:26:06.680Z",
        "created_at": "2023-09-14T16:36:23.176Z",
        "updated_at": "2023-09-14T20:47:13.863Z",
        "organization_id": "main_entity_pk"
      },
      {
        "id": "9a862f02-f44a-45b0-906b-8fd39cd4fb15",
        "title": "Global Summit for Social Change",
        "start_time": "2023-09-15T12:35:49.578Z",
        "end_time": "2023-09-15T01:30:47.344Z",
        "created_at": "2023-09-15T06:27:48.935Z",
        "updated_at": "2023-09-15T09:11:06.984Z",
        "organization_id": "main_entity_pk"
      },
      {
        "id": "607bdbc0-52be-4453-b3c0-60a38c98e25a",
        "title": "Renewable Energy Conference",
        "start_time": "2023-09-14T21:57:29.493Z",
        "end_time": "2023-09-15T11:17:24.351Z",
        "created_at": "2023-09-15T01:38:25.883Z",
        "updated_at": "2023-09-14T22:39:56.310Z",
        "organization_id": "main_entity_pk"
      },
      {
        "id": "b56bdd0e-c437-41b5-b500-6fbc99a7cf19",
        "title": "World Art Convention",
        "start_time": "2023-09-15T10:57:03.547Z",
        "end_time": "2023-09-14T21:19:35.897Z",
        "created_at": "2023-09-15T07:25:55.176Z",
        "updated_at": "2023-09-15T09:16:28.297Z",
        "organization_id": "main_entity_pk"
      }
    ],
    "participant": [
      {
        "id": "5551d6f0-b9dc-4b2c-8636-85ab0890d818",
        "joined_at": "2023-09-14T20:12:16.286Z",
        "left_at": "2023-09-15T01:25:05.255Z",
        "created_at": "2023-09-15T09:50:34.970Z",
        "updated_at": "2023-09-14T23:29:29.769Z",
        "conference_id": "9a862f02-f44a-45b0-906b-8fd39cd4fb15",
        "user_id": "user_entity_pk"
      },
      {
        "id": "1935a2c1-873d-4b1a-bf7a-af7181f128c8",
        "joined_at": "2023-09-15T11:51:38.204Z",
        "left_at": "2023-09-14T21:27:34.674Z",
        "created_at": "2023-09-15T04:38:08.734Z",
        "updated_at": "2023-09-15T08:21:25.502Z",
        "conference_id": "bf55ded2-ffe4-4705-8c08-9cffa6b8f540",
        "user_id": "user_entity_pk"
      },
      {
        "id": "96b29adb-3c95-4179-a51a-b47933d22a35",
        "joined_at": "2023-09-14T14:53:35.615Z",
        "left_at": "2023-09-15T11:03:49.039Z",
        "created_at": "2023-09-14T18:00:13.444Z",
        "updated_at": "2023-09-15T13:06:56.799Z",
        "conference_id": "9a862f02-f44a-45b0-906b-8fd39cd4fb15",
        "user_id": "user_entity_pk"
      },
      {
        "id": "50516301-7069-4618-9f66-1b6a479a7be3",
        "joined_at": "2023-09-14T23:50:14.902Z",
        "left_at": "2023-09-15T00:31:07.691Z",
        "created_at": "2023-09-15T05:42:40.880Z",
        "updated_at": "2023-09-14T15:11:44.206Z",
        "conference_id": "607bdbc0-52be-4453-b3c0-60a38c98e25a",
        "user_id": "user_entity_pk"
      },
      {
        "id": "58ba1da3-e7ba-4d43-99f4-d768fb550c11",
        "joined_at": "2023-09-14T15:51:49.903Z",
        "left_at": "2023-09-15T13:55:42.776Z",
        "created_at": "2023-09-15T05:56:47.610Z",
        "updated_at": "2023-09-14T17:21:10.012Z",
        "conference_id": "ee58effc-7aa3-4732-8d0f-c7ccd1f6a22f",
        "user_id": "user_entity_pk"
      }
    ],
    "roqUser": [
      {
        "reference": "6eb774b8-62a5-4b03-b695-cd460399b174",
        "email": "Alexandrine.Kub64@yahoo.com",
        "firstName": "Flossie",
        "lastName": "Champlin",
        "active": true,
        "avatarUrl": "https://cloudflare-ipfs.com/ipfs/Qmd3W5DuhgHirLHGVixi6V76LhCkZUz6pnFt5AJBiyvHye/avatar/636.jpg",
        "tenantId": null
      },
      {
        "reference": "67cc2152-00d0-4967-a9e4-a3be7d58e490",
        "email": "Riley_Grady28@yahoo.com",
        "firstName": "Eleonore",
        "lastName": "Terry",
        "active": true,
        "avatarUrl": "https://avatars.githubusercontent.com/u/79445134",
        "tenantId": null
      },
      {
        "reference": "693c1121-2e4c-4c7c-a238-b46a08f9ad55",
        "email": "Kailee.Kertzmann15@yahoo.com",
        "firstName": "Ana",
        "lastName": "Bogisich",
        "active": true,
        "avatarUrl": "https://avatars.githubusercontent.com/u/80724395",
        "tenantId": null
      },
      {
        "reference": "8fa92b11-3703-4013-b857-362f62e6701e",
        "email": "Hubert.Johnston@hotmail.com",
        "firstName": "Jerod",
        "lastName": "Wuckert",
        "active": true,
        "avatarUrl": "https://avatars.githubusercontent.com/u/45389542",
        "tenantId": null
      },
      {
        "reference": "7ad8bfee-c564-49bc-bc0e-444a4f0859dc",
        "email": "Sophia_Kuhn@gmail.com",
        "firstName": "Kenneth",
        "lastName": "Klein",
        "active": true,
        "avatarUrl": "https://cloudflare-ipfs.com/ipfs/Qmd3W5DuhgHirLHGVixi6V76LhCkZUz6pnFt5AJBiyvHye/avatar/835.jpg",
        "tenantId": null
      }
    ]
  },
  {
    "conference": [
      {
        "id": "711df41e-d5b1-483a-bbb5-c6ac5aefa6b5",
        "title": "International Conference on Artificial Intelligence",
        "start_time": "2023-09-14T21:50:06.421Z",
        "end_time": "2023-09-14T14:39:21.806Z",
        "created_at": "2023-09-15T01:26:56.112Z",
        "updated_at": "2023-09-15T07:32:41.531Z",
        "organization_id": "main_entity_pk"
      },
      {
        "id": "d0f17ed2-9449-4a40-818a-76c24c6acae3",
        "title": "Annual Tech Summit",
        "start_time": "2023-09-15T00:41:01.362Z",
        "end_time": "2023-09-15T12:53:45.322Z",
        "created_at": "2023-09-14T17:49:00.262Z",
        "updated_at": "2023-09-15T02:03:16.554Z",
        "organization_id": "main_entity_pk"
      },
      {
        "id": "76bbc7aa-0fdd-4421-9849-cd5b78d5997f",
        "title": "Finance Forum 2022",
        "start_time": "2023-09-15T03:44:54.200Z",
        "end_time": "2023-09-15T12:44:25.285Z",
        "created_at": "2023-09-15T00:45:51.949Z",
        "updated_at": "2023-09-14T23:30:00.751Z",
        "organization_id": "main_entity_pk"
      },
      {
        "id": "5ae79fff-00ac-49c8-aa44-495b70e8a4ae",
        "title": "Healthcare Innovation Conference",
        "start_time": "2023-09-15T12:13:30.704Z",
        "end_time": "2023-09-15T14:34:24.389Z",
        "created_at": "2023-09-15T08:41:44.451Z",
        "updated_at": "2023-09-15T09:13:32.233Z",
        "organization_id": "main_entity_pk"
      },
      {
        "id": "b88d0cfe-d8b7-4387-baa6-391d519142f2",
        "title": "Digital Learning Symposium",
        "start_time": "2023-09-14T17:13:16.649Z",
        "end_time": "2023-09-14T15:47:26.792Z",
        "created_at": "2023-09-15T04:46:07.791Z",
        "updated_at": "2023-09-15T07:49:24.854Z",
        "organization_id": "main_entity_pk"
      }
    ],
    "participant": [
      {
        "id": "b9be1911-9ac0-4269-915e-669022c0c944",
        "joined_at": "2023-09-14T17:02:43.363Z",
        "left_at": "2023-09-14T20:12:57.524Z",
        "created_at": "2023-09-15T07:13:27.562Z",
        "updated_at": "2023-09-15T00:00:14.086Z",
        "conference_id": "b88d0cfe-d8b7-4387-baa6-391d519142f2",
        "user_id": "user_entity_pk"
      },
      {
        "id": "538e20b6-0f07-4a18-a8c1-c4bf708ef23e",
        "joined_at": "2023-09-15T13:58:02.650Z",
        "left_at": "2023-09-15T12:09:27.408Z",
        "created_at": "2023-09-14T15:16:24.162Z",
        "updated_at": "2023-09-15T10:28:12.235Z",
        "conference_id": "b88d0cfe-d8b7-4387-baa6-391d519142f2",
        "user_id": "user_entity_pk"
      },
      {
        "id": "f26bf0d2-4588-41ac-b0a2-3884687d030a",
        "joined_at": "2023-09-15T01:04:47.198Z",
        "left_at": "2023-09-14T20:35:20.008Z",
        "created_at": "2023-09-15T11:22:00.929Z",
        "updated_at": "2023-09-14T19:53:16.963Z",
        "conference_id": "5ae79fff-00ac-49c8-aa44-495b70e8a4ae",
        "user_id": "user_entity_pk"
      },
      {
        "id": "a0124495-9f40-44db-a60e-896b8155f789",
        "joined_at": "2023-09-15T12:36:06.533Z",
        "left_at": "2023-09-15T13:10:09.071Z",
        "created_at": "2023-09-15T04:58:17.608Z",
        "updated_at": "2023-09-15T06:05:16.218Z",
        "conference_id": "b88d0cfe-d8b7-4387-baa6-391d519142f2",
        "user_id": "user_entity_pk"
      },
      {
        "id": "5b6fc6b0-0904-432f-9854-af08c5fb3916",
        "joined_at": "2023-09-14T22:15:02.575Z",
        "left_at": "2023-09-15T11:46:24.544Z",
        "created_at": "2023-09-15T11:03:50.640Z",
        "updated_at": "2023-09-14T23:56:58.908Z",
        "conference_id": "5ae79fff-00ac-49c8-aa44-495b70e8a4ae",
        "user_id": "user_entity_pk"
      }
    ],
    "roqUser": [
      {
        "reference": "979b3df9-3a83-48b7-bd6f-61d24185ef54",
        "email": "Kelli85@yahoo.com",
        "firstName": "Jean",
        "lastName": "Murray",
        "active": true,
        "avatarUrl": "https://avatars.githubusercontent.com/u/77915584",
        "tenantId": null
      },
      {
        "reference": "b6d69862-3ae7-4b1f-9f02-76c37c48f78f",
        "email": "Rylee.Breitenberg-Pouros52@gmail.com",
        "firstName": "Ella",
        "lastName": "Willms",
        "active": true,
        "avatarUrl": "https://cloudflare-ipfs.com/ipfs/Qmd3W5DuhgHirLHGVixi6V76LhCkZUz6pnFt5AJBiyvHye/avatar/496.jpg",
        "tenantId": null
      },
      {
        "reference": "609e6d32-27d9-4055-95a8-b2a4271c3519",
        "email": "Zoila.Bernhard@hotmail.com",
        "firstName": "Helmer",
        "lastName": "Kassulke",
        "active": true,
        "avatarUrl": "https://cloudflare-ipfs.com/ipfs/Qmd3W5DuhgHirLHGVixi6V76LhCkZUz6pnFt5AJBiyvHye/avatar/451.jpg",
        "tenantId": null
      },
      {
        "reference": "aa7b5b71-a52c-49ca-9ff3-e3a1cda8c18e",
        "email": "Harmony.Hermiston28@hotmail.com",
        "firstName": "Terrell",
        "lastName": "Shanahan",
        "active": true,
        "avatarUrl": "https://avatars.githubusercontent.com/u/71080750",
        "tenantId": null
      },
      {
        "reference": "1c55e715-72bf-4604-8004-db11f7366ead",
        "email": "Haven43@yahoo.com",
        "firstName": "Maymie",
        "lastName": "Wisoky",
        "active": true,
        "avatarUrl": "https://cloudflare-ipfs.com/ipfs/Qmd3W5DuhgHirLHGVixi6V76LhCkZUz6pnFt5AJBiyvHye/avatar/1168.jpg",
        "tenantId": null
      }
    ]
  },
  {
    "conference": [
      {
        "id": "3d164cac-84f1-4769-9901-ffb7b3d9a5ba",
        "title": "International Conference on Artificial Intelligence",
        "start_time": "2023-09-15T08:10:54.701Z",
        "end_time": "2023-09-14T14:38:33.151Z",
        "created_at": "2023-09-14T18:05:42.528Z",
        "updated_at": "2023-09-15T10:23:13.558Z",
        "organization_id": "main_entity_pk"
      },
      {
        "id": "cfc344e1-8e1c-4147-adbe-acef3148be49",
        "title": "Annual Global Summit for Sustainable Development",
        "start_time": "2023-09-15T06:06:33.285Z",
        "end_time": "2023-09-15T08:10:49.139Z",
        "created_at": "2023-09-15T02:13:57.717Z",
        "updated_at": "2023-09-15T02:37:40.631Z",
        "organization_id": "main_entity_pk"
      },
      {
        "id": "2c13fa3c-745d-4062-b089-9d3ec2e6eeaa",
        "title": "Worldwide Healthcare Innovation Forum",
        "start_time": "2023-09-14T17:42:42.534Z",
        "end_time": "2023-09-14T19:37:52.695Z",
        "created_at": "2023-09-15T00:55:36.893Z",
        "updated_at": "2023-09-14T16:19:41.059Z",
        "organization_id": "main_entity_pk"
      },
      {
        "id": "c063e8bb-0667-4e90-93b0-21595adef644",
        "title": "E-Commerce Revolution Conference",
        "start_time": "2023-09-14T19:27:05.287Z",
        "end_time": "2023-09-15T05:55:26.557Z",
        "created_at": "2023-09-15T08:36:01.904Z",
        "updated_at": "2023-09-15T10:44:31.515Z",
        "organization_id": "main_entity_pk"
      },
      {
        "id": "7ef7efcc-e635-405b-89b0-e58814ddfa8c",
        "title": "Future of Education Symposium",
        "start_time": "2023-09-14T21:24:50.642Z",
        "end_time": "2023-09-15T04:13:52.640Z",
        "created_at": "2023-09-15T02:57:25.317Z",
        "updated_at": "2023-09-15T13:20:33.712Z",
        "organization_id": "main_entity_pk"
      }
    ],
    "participant": [
      {
        "id": "bbed845a-eca2-40b3-ae25-baa44dece9b9",
        "joined_at": "2023-09-15T08:52:16.192Z",
        "left_at": "2023-09-14T19:15:43.275Z",
        "created_at": "2023-09-14T17:13:47.575Z",
        "updated_at": "2023-09-15T02:50:59.385Z",
        "conference_id": "7ef7efcc-e635-405b-89b0-e58814ddfa8c",
        "user_id": "user_entity_pk"
      },
      {
        "id": "4af80cb2-7e0b-47c0-b7cb-36b17670cd20",
        "joined_at": "2023-09-15T00:39:41.211Z",
        "left_at": "2023-09-15T07:41:03.112Z",
        "created_at": "2023-09-15T08:27:01.752Z",
        "updated_at": "2023-09-15T09:16:05.812Z",
        "conference_id": "3d164cac-84f1-4769-9901-ffb7b3d9a5ba",
        "user_id": "user_entity_pk"
      },
      {
        "id": "a4902f54-19cb-41ed-b2aa-9d721ed94823",
        "joined_at": "2023-09-15T02:33:19.476Z",
        "left_at": "2023-09-15T08:05:23.231Z",
        "created_at": "2023-09-14T16:35:13.466Z",
        "updated_at": "2023-09-15T03:49:09.984Z",
        "conference_id": "3d164cac-84f1-4769-9901-ffb7b3d9a5ba",
        "user_id": "user_entity_pk"
      },
      {
        "id": "ef112e42-1744-4d7d-b1be-9f76f7779beb",
        "joined_at": "2023-09-15T03:21:00.275Z",
        "left_at": "2023-09-14T19:07:53.365Z",
        "created_at": "2023-09-15T07:10:00.384Z",
        "updated_at": "2023-09-14T21:08:45.375Z",
        "conference_id": "cfc344e1-8e1c-4147-adbe-acef3148be49",
        "user_id": "user_entity_pk"
      },
      {
        "id": "8beac0fb-dcaa-490a-a4a2-60035ec07858",
        "joined_at": "2023-09-15T08:02:00.754Z",
        "left_at": "2023-09-15T08:37:02.679Z",
        "created_at": "2023-09-15T14:17:47.000Z",
        "updated_at": "2023-09-15T10:22:47.560Z",
        "conference_id": "2c13fa3c-745d-4062-b089-9d3ec2e6eeaa",
        "user_id": "user_entity_pk"
      }
    ],
    "roqUser": [
      {
        "reference": "89c64df3-cac3-4a2f-b0cb-ecc944369d1e",
        "email": "Beulah_Yost-Stanton@hotmail.com",
        "firstName": "Carli",
        "lastName": "Feest",
        "active": true,
        "avatarUrl": "https://cloudflare-ipfs.com/ipfs/Qmd3W5DuhgHirLHGVixi6V76LhCkZUz6pnFt5AJBiyvHye/avatar/201.jpg",
        "tenantId": null
      },
      {
        "reference": "65bc8f98-45b3-47bd-b730-c225527001df",
        "email": "Augustus_McKenzie@yahoo.com",
        "firstName": "Fay",
        "lastName": "Ruecker",
        "active": true,
        "avatarUrl": "https://avatars.githubusercontent.com/u/6155163",
        "tenantId": null
      },
      {
        "reference": "0050792c-7232-47d6-83b5-0be9a3e8c313",
        "email": "Leanna55@hotmail.com",
        "firstName": "Savannah",
        "lastName": "Ritchie",
        "active": true,
        "avatarUrl": "https://cloudflare-ipfs.com/ipfs/Qmd3W5DuhgHirLHGVixi6V76LhCkZUz6pnFt5AJBiyvHye/avatar/1246.jpg",
        "tenantId": null
      },
      {
        "reference": "9fd80c4e-1717-4489-8535-c024ffca91a4",
        "email": "Steve3@yahoo.com",
        "firstName": "Neoma",
        "lastName": "Schaefer",
        "active": true,
        "avatarUrl": "https://avatars.githubusercontent.com/u/1295450",
        "tenantId": null
      },
      {
        "reference": "50e28131-5076-4298-883f-de772a7d18c8",
        "email": "Frieda_Mraz@yahoo.com",
        "firstName": "Ramona",
        "lastName": "Kozey",
        "active": true,
        "avatarUrl": "https://avatars.githubusercontent.com/u/68764266",
        "tenantId": null
      }
    ]
  },
  {
    "conference": [
      {
        "id": "90b3bdd3-b27a-4693-a11c-6b0186172a98",
        "title": "International Conference on Sustainable Development",
        "start_time": "2023-09-15T02:00:11.308Z",
        "end_time": "2023-09-15T00:09:36.289Z",
        "created_at": "2023-09-15T08:17:59.011Z",
        "updated_at": "2023-09-14T21:38:42.197Z",
        "organization_id": "main_entity_pk"
      },
      {
        "id": "7bfd4967-96a1-4770-a560-50b6b88d9e50",
        "title": "TechX Summit",
        "start_time": "2023-09-15T11:18:37.736Z",
        "end_time": "2023-09-14T16:22:45.293Z",
        "created_at": "2023-09-14T17:26:33.773Z",
        "updated_at": "2023-09-14T18:44:09.536Z",
        "organization_id": "main_entity_pk"
      },
      {
        "id": "e57a61a7-89bc-4415-9b5d-19ae7a22539f",
        "title": "Global Business Forum",
        "start_time": "2023-09-14T18:44:12.341Z",
        "end_time": "2023-09-15T03:39:29.863Z",
        "created_at": "2023-09-15T08:57:41.585Z",
        "updated_at": "2023-09-15T02:29:52.972Z",
        "organization_id": "main_entity_pk"
      },
      {
        "id": "36ecd2a3-004e-4d7e-a8ac-2ce04ba98f8b",
        "title": "Healthcare Innovation Conference",
        "start_time": "2023-09-14T15:36:43.183Z",
        "end_time": "2023-09-15T00:17:08.806Z",
        "created_at": "2023-09-15T09:37:46.549Z",
        "updated_at": "2023-09-15T08:31:42.732Z",
        "organization_id": "main_entity_pk"
      },
      {
        "id": "c8ac9649-c143-41b4-ac80-c7df47b08ff8",
        "title": "Fashion Forward Symposium",
        "start_time": "2023-09-15T05:33:12.872Z",
        "end_time": "2023-09-15T08:51:58.854Z",
        "created_at": "2023-09-14T22:47:27.993Z",
        "updated_at": "2023-09-14T19:04:36.976Z",
        "organization_id": "main_entity_pk"
      }
    ],
    "participant": [
      {
        "id": "dfc7b7ae-ecc6-4ad6-9403-27b3db45d156",
        "joined_at": "2023-09-15T03:16:11.349Z",
        "left_at": "2023-09-14T20:06:27.409Z",
        "created_at": "2023-09-15T06:00:13.339Z",
        "updated_at": "2023-09-15T09:47:38.930Z",
        "conference_id": "e57a61a7-89bc-4415-9b5d-19ae7a22539f",
        "user_id": "user_entity_pk"
      },
      {
        "id": "0d6010b3-1c0f-42e8-822a-6600a7daa85d",
        "joined_at": "2023-09-14T21:47:09.635Z",
        "left_at": "2023-09-15T09:30:53.646Z",
        "created_at": "2023-09-14T22:49:42.278Z",
        "updated_at": "2023-09-15T13:09:52.613Z",
        "conference_id": "7bfd4967-96a1-4770-a560-50b6b88d9e50",
        "user_id": "user_entity_pk"
      },
      {
        "id": "a7cf5729-1cb2-4549-8813-93fb744c1bc7",
        "joined_at": "2023-09-14T23:43:24.839Z",
        "left_at": "2023-09-15T09:09:37.878Z",
        "created_at": "2023-09-14T15:22:09.075Z",
        "updated_at": "2023-09-14T18:54:55.648Z",
        "conference_id": "36ecd2a3-004e-4d7e-a8ac-2ce04ba98f8b",
        "user_id": "user_entity_pk"
      },
      {
        "id": "33de7095-1e08-4be3-95b9-70fb38ef794a",
        "joined_at": "2023-09-14T18:31:34.820Z",
        "left_at": "2023-09-14T22:20:54.060Z",
        "created_at": "2023-09-14T17:59:48.565Z",
        "updated_at": "2023-09-14T21:51:31.686Z",
        "conference_id": "c8ac9649-c143-41b4-ac80-c7df47b08ff8",
        "user_id": "user_entity_pk"
      },
      {
        "id": "2a944da4-1e35-4524-ba88-44d0f4a300ea",
        "joined_at": "2023-09-15T01:24:07.708Z",
        "left_at": "2023-09-15T10:51:41.315Z",
        "created_at": "2023-09-15T01:53:24.168Z",
        "updated_at": "2023-09-15T11:23:36.056Z",
        "conference_id": "7bfd4967-96a1-4770-a560-50b6b88d9e50",
        "user_id": "user_entity_pk"
      }
    ],
    "roqUser": [
      {
        "reference": "2ed02fac-2b15-497c-8209-9211ea1a69ee",
        "email": "Zoie_Schulist@gmail.com",
        "firstName": "Arturo",
        "lastName": "Bins",
        "active": true,
        "avatarUrl": "https://cloudflare-ipfs.com/ipfs/Qmd3W5DuhgHirLHGVixi6V76LhCkZUz6pnFt5AJBiyvHye/avatar/932.jpg",
        "tenantId": null
      },
      {
        "reference": "d82bee58-19db-46ef-94b7-6ada3f84c179",
        "email": "Kurtis_Cormier16@hotmail.com",
        "firstName": "Francisca",
        "lastName": "Hilll",
        "active": true,
        "avatarUrl": "https://cloudflare-ipfs.com/ipfs/Qmd3W5DuhgHirLHGVixi6V76LhCkZUz6pnFt5AJBiyvHye/avatar/173.jpg",
        "tenantId": null
      },
      {
        "reference": "2581c0df-620a-4ce0-b110-357afca1cc48",
        "email": "Antonetta_Conroy@hotmail.com",
        "firstName": "Flavie",
        "lastName": "Adams",
        "active": true,
        "avatarUrl": "https://cloudflare-ipfs.com/ipfs/Qmd3W5DuhgHirLHGVixi6V76LhCkZUz6pnFt5AJBiyvHye/avatar/736.jpg",
        "tenantId": null
      },
      {
        "reference": "5f0ef611-c2e8-4a59-b90a-6f8a1a4a8aa6",
        "email": "Fabiola54@hotmail.com",
        "firstName": "Aron",
        "lastName": "Kessler",
        "active": true,
        "avatarUrl": "https://cloudflare-ipfs.com/ipfs/Qmd3W5DuhgHirLHGVixi6V76LhCkZUz6pnFt5AJBiyvHye/avatar/707.jpg",
        "tenantId": null
      },
      {
        "reference": "b306aa0f-ab5b-42a7-917a-f11ee2bc74f4",
        "email": "Ernesto.Huel@gmail.com",
        "firstName": "Chyna",
        "lastName": "Doyle",
        "active": true,
        "avatarUrl": "https://cloudflare-ipfs.com/ipfs/Qmd3W5DuhgHirLHGVixi6V76LhCkZUz6pnFt5AJBiyvHye/avatar/1000.jpg",
        "tenantId": null
      }
    ]
  },
  {
    "conference": [
      {
        "id": "0a1b802d-a101-411e-907e-b8dfa4a0e9a9",
        "title": "International Conference on Sustainable Energy",
        "start_time": "2023-09-14T23:01:48.954Z",
        "end_time": "2023-09-14T21:40:30.951Z",
        "created_at": "2023-09-15T02:01:17.234Z",
        "updated_at": "2023-09-14T15:47:05.971Z",
        "organization_id": "main_entity_pk"
      },
      {
        "id": "64b95172-5c0a-44e9-b52f-7ebcf912fc00",
        "title": "Annual Tech Summit",
        "start_time": "2023-09-14T14:53:06.100Z",
        "end_time": "2023-09-15T05:47:05.876Z",
        "created_at": "2023-09-15T12:59:15.283Z",
        "updated_at": "2023-09-14T21:28:54.076Z",
        "organization_id": "main_entity_pk"
      },
      {
        "id": "d4e9975e-09c0-4432-baed-9aff623667f9",
        "title": "Global Healthcare Symposium",
        "start_time": "2023-09-15T10:20:44.645Z",
        "end_time": "2023-09-15T01:27:21.261Z",
        "created_at": "2023-09-15T03:33:54.073Z",
        "updated_at": "2023-09-15T10:51:54.364Z",
        "organization_id": "main_entity_pk"
      },
      {
        "id": "f06fe893-62fd-4875-aa0c-21e2cf375c89",
        "title": "Fashion Forward Expo",
        "start_time": "2023-09-15T00:08:23.728Z",
        "end_time": "2023-09-14T16:58:23.646Z",
        "created_at": "2023-09-15T01:15:40.987Z",
        "updated_at": "2023-09-15T06:57:44.827Z",
        "organization_id": "main_entity_pk"
      },
      {
        "id": "ca21d652-1793-49ad-9cfc-6b182f0f44a5",
        "title": "World Education Conference",
        "start_time": "2023-09-15T13:47:11.385Z",
        "end_time": "2023-09-14T21:14:52.078Z",
        "created_at": "2023-09-15T08:59:10.501Z",
        "updated_at": "2023-09-15T03:24:18.785Z",
        "organization_id": "main_entity_pk"
      }
    ],
    "participant": [
      {
        "id": "3de8bb62-e7e5-4601-a379-2fc9004e5616",
        "joined_at": "2023-09-15T05:19:42.436Z",
        "left_at": "2023-09-15T09:29:08.927Z",
        "created_at": "2023-09-15T03:39:16.025Z",
        "updated_at": "2023-09-14T17:30:50.981Z",
        "conference_id": "d4e9975e-09c0-4432-baed-9aff623667f9",
        "user_id": "user_entity_pk"
      },
      {
        "id": "91e24186-4c09-4b5e-88a3-d24088b36eef",
        "joined_at": "2023-09-14T22:19:05.309Z",
        "left_at": "2023-09-14T21:27:23.205Z",
        "created_at": "2023-09-14T22:50:23.762Z",
        "updated_at": "2023-09-14T21:59:05.255Z",
        "conference_id": "ca21d652-1793-49ad-9cfc-6b182f0f44a5",
        "user_id": "user_entity_pk"
      },
      {
        "id": "c40c8dfb-e367-42b4-b6c0-11826a35a666",
        "joined_at": "2023-09-15T11:26:27.526Z",
        "left_at": "2023-09-14T16:01:45.578Z",
        "created_at": "2023-09-15T00:24:14.394Z",
        "updated_at": "2023-09-15T01:23:04.631Z",
        "conference_id": "f06fe893-62fd-4875-aa0c-21e2cf375c89",
        "user_id": "user_entity_pk"
      },
      {
        "id": "3b55993d-8766-4968-90b1-bfdf7c46d6b3",
        "joined_at": "2023-09-14T17:31:32.305Z",
        "left_at": "2023-09-15T01:34:03.507Z",
        "created_at": "2023-09-14T16:22:26.153Z",
        "updated_at": "2023-09-14T18:54:45.800Z",
        "conference_id": "ca21d652-1793-49ad-9cfc-6b182f0f44a5",
        "user_id": "user_entity_pk"
      },
      {
        "id": "28a3bc18-6882-4d44-8a21-fd252fd78fcb",
        "joined_at": "2023-09-14T23:41:07.350Z",
        "left_at": "2023-09-15T09:07:33.678Z",
        "created_at": "2023-09-15T00:12:49.342Z",
        "updated_at": "2023-09-15T10:56:47.568Z",
        "conference_id": "ca21d652-1793-49ad-9cfc-6b182f0f44a5",
        "user_id": "user_entity_pk"
      }
    ],
    "roqUser": [
      {
        "reference": "46a2e965-fedb-4070-bb36-ba887e4aacf3",
        "email": "Nathanial.OConner-Will71@yahoo.com",
        "firstName": "Tatum",
        "lastName": "Thompson-Denesik",
        "active": true,
        "avatarUrl": "https://avatars.githubusercontent.com/u/42864707",
        "tenantId": null
      },
      {
        "reference": "601800d6-c7ee-4f30-b5d4-f85a5e6991e0",
        "email": "Chris.Roberts55@gmail.com",
        "firstName": "Aletha",
        "lastName": "Hansen",
        "active": true,
        "avatarUrl": "https://avatars.githubusercontent.com/u/77469948",
        "tenantId": null
      },
      {
        "reference": "28e3c929-0ffd-45de-8cc0-37e0c12cbbe6",
        "email": "Ferne.Schaden97@hotmail.com",
        "firstName": "Isaias",
        "lastName": "Cole",
        "active": true,
        "avatarUrl": "https://avatars.githubusercontent.com/u/57338728",
        "tenantId": null
      },
      {
        "reference": "52c0ff83-1c53-452f-b83b-cab475838221",
        "email": "Nelda38@hotmail.com",
        "firstName": "Van",
        "lastName": "Heidenreich",
        "active": true,
        "avatarUrl": "https://cloudflare-ipfs.com/ipfs/Qmd3W5DuhgHirLHGVixi6V76LhCkZUz6pnFt5AJBiyvHye/avatar/101.jpg",
        "tenantId": null
      },
      {
        "reference": "d645237c-d758-4e1f-8945-c3f374f579e5",
        "email": "Kian.DAmore48@yahoo.com",
        "firstName": "Cletus",
        "lastName": "Greenholt",
        "active": true,
        "avatarUrl": "https://avatars.githubusercontent.com/u/29552197",
        "tenantId": null
      }
    ]
  },
  {
    "conference": [
      {
        "id": "01b15406-5344-44f6-a66d-a88e177924eb",
        "title": "International Summit on Renewable Energy",
        "start_time": "2023-09-14T22:27:36.121Z",
        "end_time": "2023-09-14T17:16:31.737Z",
        "created_at": "2023-09-15T02:35:33.459Z",
        "updated_at": "2023-09-14T22:15:28.573Z",
        "organization_id": "main_entity_pk"
      },
      {
        "id": "e8166217-77fb-4838-8e20-875802679cf7",
        "title": "TechX Conference",
        "start_time": "2023-09-14T21:27:16.093Z",
        "end_time": "2023-09-15T04:04:33.064Z",
        "created_at": "2023-09-14T19:10:07.773Z",
        "updated_at": "2023-09-14T20:48:18.875Z",
        "organization_id": "main_entity_pk"
      },
      {
        "id": "bf93441a-ef49-41f1-9e8e-df7e38096331",
        "title": "Global Business Forum",
        "start_time": "2023-09-15T01:23:48.951Z",
        "end_time": "2023-09-15T05:39:53.882Z",
        "created_at": "2023-09-15T03:57:19.701Z",
        "updated_at": "2023-09-15T05:01:51.692Z",
        "organization_id": "main_entity_pk"
      },
      {
        "id": "0db0c749-7b2a-409c-bdf4-a9456d4f825c",
        "title": "Education Innovators Summit",
        "start_time": "2023-09-14T16:45:35.646Z",
        "end_time": "2023-09-15T00:09:36.750Z",
        "created_at": "2023-09-14T19:05:50.629Z",
        "updated_at": "2023-09-14T22:39:46.053Z",
        "organization_id": "main_entity_pk"
      },
      {
        "id": "db4f7947-7bb3-468e-a47d-b0244cdd92c4",
        "title": "Healthcare Symposium",
        "start_time": "2023-09-14T21:22:10.727Z",
        "end_time": "2023-09-14T18:10:57.388Z",
        "created_at": "2023-09-15T04:51:20.806Z",
        "updated_at": "2023-09-15T11:04:39.565Z",
        "organization_id": "main_entity_pk"
      }
    ],
    "participant": [
      {
        "id": "18788d1f-8bd6-41b5-9410-5cc928dbdad0",
        "joined_at": "2023-09-14T17:28:09.160Z",
        "left_at": "2023-09-15T04:54:57.304Z",
        "created_at": "2023-09-14T15:05:43.133Z",
        "updated_at": "2023-09-14T17:32:10.108Z",
        "conference_id": "bf93441a-ef49-41f1-9e8e-df7e38096331",
        "user_id": "user_entity_pk"
      },
      {
        "id": "5b022cd0-c83a-47b8-aa09-1496e98b0ece",
        "joined_at": "2023-09-14T17:28:07.238Z",
        "left_at": "2023-09-14T23:38:14.283Z",
        "created_at": "2023-09-14T19:11:16.793Z",
        "updated_at": "2023-09-14T15:45:46.100Z",
        "conference_id": "db4f7947-7bb3-468e-a47d-b0244cdd92c4",
        "user_id": "user_entity_pk"
      },
      {
        "id": "6e874b4d-8b73-494a-a810-06aa7ebf1b76",
        "joined_at": "2023-09-15T02:05:50.790Z",
        "left_at": "2023-09-14T22:52:25.241Z",
        "created_at": "2023-09-15T10:16:29.615Z",
        "updated_at": "2023-09-14T17:07:49.138Z",
        "conference_id": "db4f7947-7bb3-468e-a47d-b0244cdd92c4",
        "user_id": "user_entity_pk"
      },
      {
        "id": "61301ebb-3416-404c-a811-05af6879b37f",
        "joined_at": "2023-09-14T18:18:45.673Z",
        "left_at": "2023-09-14T17:53:23.773Z",
        "created_at": "2023-09-15T03:39:16.931Z",
        "updated_at": "2023-09-14T16:17:55.558Z",
        "conference_id": "0db0c749-7b2a-409c-bdf4-a9456d4f825c",
        "user_id": "user_entity_pk"
      },
      {
        "id": "42fed7e2-67da-4815-b6d0-6ae68e1683b3",
        "joined_at": "2023-09-15T00:23:52.575Z",
        "left_at": "2023-09-15T08:04:23.562Z",
        "created_at": "2023-09-14T20:10:05.817Z",
        "updated_at": "2023-09-14T18:32:23.465Z",
        "conference_id": "01b15406-5344-44f6-a66d-a88e177924eb",
        "user_id": "user_entity_pk"
      }
    ],
    "roqUser": [
      {
        "reference": "38558c5a-99fe-4a03-9fa7-b8b4389fafd6",
        "email": "Emilia_Runolfsson41@gmail.com",
        "firstName": "Alverta",
        "lastName": "Schamberger",
        "active": true,
        "avatarUrl": "https://avatars.githubusercontent.com/u/41531217",
        "tenantId": null
      },
      {
        "reference": "99ad4b97-aeed-452d-bd8a-4541ea5c0716",
        "email": "Kiel_Kuhn8@yahoo.com",
        "firstName": "Ronny",
        "lastName": "Dietrich",
        "active": true,
        "avatarUrl": "https://cloudflare-ipfs.com/ipfs/Qmd3W5DuhgHirLHGVixi6V76LhCkZUz6pnFt5AJBiyvHye/avatar/896.jpg",
        "tenantId": null
      },
      {
        "reference": "ba3abeaf-b4ed-46a1-b575-2b32b01ddeda",
        "email": "Natasha.Schoen45@hotmail.com",
        "firstName": "Nasir",
        "lastName": "Osinski",
        "active": true,
        "avatarUrl": "https://avatars.githubusercontent.com/u/8135483",
        "tenantId": null
      },
      {
        "reference": "8faca717-645a-4e54-8c06-bfd9dd0aab09",
        "email": "Jaycee_Larson@hotmail.com",
        "firstName": "Brent",
        "lastName": "Mayert",
        "active": true,
        "avatarUrl": "https://cloudflare-ipfs.com/ipfs/Qmd3W5DuhgHirLHGVixi6V76LhCkZUz6pnFt5AJBiyvHye/avatar/1045.jpg",
        "tenantId": null
      },
      {
        "reference": "d2f985cc-678c-4b2e-b0ea-2dd3c1f6e5e7",
        "email": "Troy.Romaguera@yahoo.com",
        "firstName": "Rosendo",
        "lastName": "Hintz",
        "active": true,
        "avatarUrl": "https://avatars.githubusercontent.com/u/39245536",
        "tenantId": null
      }
    ]
  },
  {
    "conference": [
      {
        "id": "f263455c-6bdf-4e32-8093-a1bf770a8505",
        "title": "International Conference on Artificial Intelligence",
        "start_time": "2023-09-15T13:56:32.413Z",
        "end_time": "2023-09-14T16:35:38.229Z",
        "created_at": "2023-09-14T21:09:18.728Z",
        "updated_at": "2023-09-14T23:48:05.522Z",
        "organization_id": "main_entity_pk"
      },
      {
        "id": "d081e104-a38d-41fa-b3e7-c61d9a6130b7",
        "title": "Annual Global Business Summit",
        "start_time": "2023-09-14T15:06:51.155Z",
        "end_time": "2023-09-15T08:36:41.786Z",
        "created_at": "2023-09-15T12:09:15.310Z",
        "updated_at": "2023-09-15T07:14:58.420Z",
        "organization_id": "main_entity_pk"
      },
      {
        "id": "d75bbebe-6753-4b91-850f-105c456c742e",
        "title": "Worldwide Environmental Sustainability Forum",
        "start_time": "2023-09-14T23:23:17.790Z",
        "end_time": "2023-09-14T22:26:33.566Z",
        "created_at": "2023-09-15T10:21:30.683Z",
        "updated_at": "2023-09-14T18:23:13.316Z",
        "organization_id": "main_entity_pk"
      },
      {
        "id": "6008cd0c-507e-4f87-954a-2d0430374009",
        "title": "Healthcare Innovation Conference",
        "start_time": "2023-09-15T01:35:17.035Z",
        "end_time": "2023-09-14T22:35:04.300Z",
        "created_at": "2023-09-15T09:42:14.209Z",
        "updated_at": "2023-09-14T21:16:36.708Z",
        "organization_id": "main_entity_pk"
      },
      {
        "id": "e2d97726-af43-45e6-8d9e-fe2236da3bb8",
        "title": "Finance and Banking Symposium",
        "start_time": "2023-09-15T11:54:46.640Z",
        "end_time": "2023-09-15T08:16:58.924Z",
        "created_at": "2023-09-14T22:38:53.773Z",
        "updated_at": "2023-09-15T01:51:01.333Z",
        "organization_id": "main_entity_pk"
      }
    ],
    "participant": [
      {
        "id": "63fb1694-63c1-428b-a999-becce6d7d5c4",
        "joined_at": "2023-09-15T11:33:24.884Z",
        "left_at": "2023-09-14T16:06:25.669Z",
        "created_at": "2023-09-15T01:17:11.769Z",
        "updated_at": "2023-09-14T17:40:43.006Z",
        "conference_id": "6008cd0c-507e-4f87-954a-2d0430374009",
        "user_id": "user_entity_pk"
      },
      {
        "id": "936b6748-b823-46b3-852b-cceec08695cf",
        "joined_at": "2023-09-15T12:04:51.988Z",
        "left_at": "2023-09-15T06:52:36.515Z",
        "created_at": "2023-09-15T05:56:45.444Z",
        "updated_at": "2023-09-15T05:19:31.097Z",
        "conference_id": "d081e104-a38d-41fa-b3e7-c61d9a6130b7",
        "user_id": "user_entity_pk"
      },
      {
        "id": "d718d961-7652-4ee5-a5fb-6072abae9ec9",
        "joined_at": "2023-09-15T14:19:02.693Z",
        "left_at": "2023-09-14T15:40:02.120Z",
        "created_at": "2023-09-14T15:07:24.336Z",
        "updated_at": "2023-09-15T00:18:24.151Z",
        "conference_id": "d081e104-a38d-41fa-b3e7-c61d9a6130b7",
        "user_id": "user_entity_pk"
      },
      {
        "id": "2d28a1bc-f133-4350-bcf6-e97c6cb84056",
        "joined_at": "2023-09-15T05:18:12.586Z",
        "left_at": "2023-09-14T22:40:09.808Z",
        "created_at": "2023-09-14T17:14:48.909Z",
        "updated_at": "2023-09-15T08:38:07.181Z",
        "conference_id": "6008cd0c-507e-4f87-954a-2d0430374009",
        "user_id": "user_entity_pk"
      },
      {
        "id": "90845d77-d0b4-4c65-93ca-d65b2717b35c",
        "joined_at": "2023-09-15T01:47:29.447Z",
        "left_at": "2023-09-15T07:21:45.906Z",
        "created_at": "2023-09-15T07:04:30.197Z",
        "updated_at": "2023-09-14T18:52:30.920Z",
        "conference_id": "d081e104-a38d-41fa-b3e7-c61d9a6130b7",
        "user_id": "user_entity_pk"
      }
    ],
    "roqUser": [
      {
        "reference": "4e0b8d97-6dae-4c1b-a258-c5741ddc036a",
        "email": "Dorcas.Roberts@yahoo.com",
        "firstName": "Jamar",
        "lastName": "Cassin",
        "active": true,
        "avatarUrl": "https://avatars.githubusercontent.com/u/276469",
        "tenantId": null
      },
      {
        "reference": "214f2322-184f-4180-a368-58d2bfad36f5",
        "email": "Franz.Davis@gmail.com",
        "firstName": "Assunta",
        "lastName": "Skiles",
        "active": true,
        "avatarUrl": "https://cloudflare-ipfs.com/ipfs/Qmd3W5DuhgHirLHGVixi6V76LhCkZUz6pnFt5AJBiyvHye/avatar/843.jpg",
        "tenantId": null
      },
      {
        "reference": "23831cdf-e8fb-4e97-97a2-127f67d19216",
        "email": "Alivia71@yahoo.com",
        "firstName": "Katelin",
        "lastName": "Kuvalis",
        "active": true,
        "avatarUrl": "https://avatars.githubusercontent.com/u/36194081",
        "tenantId": null
      },
      {
        "reference": "a1647dc1-fc32-4bd3-90f7-bcc79e6daae8",
        "email": "Loraine74@hotmail.com",
        "firstName": "Hardy",
        "lastName": "Hills",
        "active": true,
        "avatarUrl": "https://avatars.githubusercontent.com/u/70175848",
        "tenantId": null
      },
      {
        "reference": "24b3a66e-1608-4010-ba06-f10ec708bb5d",
        "email": "Akeem_Marvin90@yahoo.com",
        "firstName": "Orie",
        "lastName": "Leuschke",
        "active": true,
        "avatarUrl": "https://cloudflare-ipfs.com/ipfs/Qmd3W5DuhgHirLHGVixi6V76LhCkZUz6pnFt5AJBiyvHye/avatar/202.jpg",
        "tenantId": null
      }
    ]
  },
  {
    "conference": [
      {
        "id": "5080eeab-7aed-4c34-9233-aeb3ec99189c",
        "title": "International Conference on Artificial Intelligence",
        "start_time": "2023-09-15T02:52:50.349Z",
        "end_time": "2023-09-15T13:59:08.563Z",
        "created_at": "2023-09-15T00:09:57.352Z",
        "updated_at": "2023-09-15T02:54:43.848Z",
        "organization_id": "main_entity_pk"
      },
      {
        "id": "1f9f834e-13f9-4d74-ac56-3cc75361255e",
        "title": "Annual Global Business Summit",
        "start_time": "2023-09-15T00:40:10.394Z",
        "end_time": "2023-09-15T00:52:31.331Z",
        "created_at": "2023-09-15T03:02:40.179Z",
        "updated_at": "2023-09-15T05:33:05.895Z",
        "organization_id": "main_entity_pk"
      },
      {
        "id": "e27bc3c4-6a71-46d6-a726-da181c1fdc3e",
        "title": "World Health Summit",
        "start_time": "2023-09-15T04:00:28.334Z",
        "end_time": "2023-09-15T12:11:14.968Z",
        "created_at": "2023-09-15T04:30:23.935Z",
        "updated_at": "2023-09-15T05:40:46.168Z",
        "organization_id": "main_entity_pk"
      },
      {
        "id": "0ee0b761-e16a-4b2c-af33-32c0c49b9011",
        "title": "Sustainable Fashion Forum",
        "start_time": "2023-09-14T17:31:06.320Z",
        "end_time": "2023-09-14T19:52:12.455Z",
        "created_at": "2023-09-14T16:30:46.438Z",
        "updated_at": "2023-09-15T05:44:34.287Z",
        "organization_id": "main_entity_pk"
      },
      {
        "id": "46abc432-772c-4fa2-8b51-41300f4947ed",
        "title": "Tech Innovators Conference",
        "start_time": "2023-09-15T12:32:34.195Z",
        "end_time": "2023-09-14T20:03:57.162Z",
        "created_at": "2023-09-15T08:08:23.586Z",
        "updated_at": "2023-09-14T15:35:47.541Z",
        "organization_id": "main_entity_pk"
      }
    ],
    "participant": [
      {
        "id": "02730379-35a5-4b78-a70d-0f1708cbc520",
        "joined_at": "2023-09-14T16:09:57.142Z",
        "left_at": "2023-09-15T01:21:16.486Z",
        "created_at": "2023-09-15T09:55:53.410Z",
        "updated_at": "2023-09-14T22:21:25.568Z",
        "conference_id": "1f9f834e-13f9-4d74-ac56-3cc75361255e",
        "user_id": "user_entity_pk"
      },
      {
        "id": "05cfff18-45a7-4e09-a147-ef52dbe6e4c5",
        "joined_at": "2023-09-15T02:19:39.367Z",
        "left_at": "2023-09-14T23:18:02.914Z",
        "created_at": "2023-09-15T08:49:13.249Z",
        "updated_at": "2023-09-15T05:05:30.062Z",
        "conference_id": "5080eeab-7aed-4c34-9233-aeb3ec99189c",
        "user_id": "user_entity_pk"
      },
      {
        "id": "fc71d462-111a-44e7-b4bc-da23200dc0ab",
        "joined_at": "2023-09-14T15:09:07.405Z",
        "left_at": "2023-09-14T23:25:51.547Z",
        "created_at": "2023-09-14T17:25:46.033Z",
        "updated_at": "2023-09-15T00:36:40.854Z",
        "conference_id": "e27bc3c4-6a71-46d6-a726-da181c1fdc3e",
        "user_id": "user_entity_pk"
      },
      {
        "id": "ac301eb0-2482-40a8-8671-abd7c67ab8ff",
        "joined_at": "2023-09-15T13:39:55.019Z",
        "left_at": "2023-09-15T04:23:57.190Z",
        "created_at": "2023-09-14T21:22:03.238Z",
        "updated_at": "2023-09-15T12:14:34.078Z",
        "conference_id": "1f9f834e-13f9-4d74-ac56-3cc75361255e",
        "user_id": "user_entity_pk"
      },
      {
        "id": "88589d3c-97bf-42c1-8080-067cb1e1bd75",
        "joined_at": "2023-09-15T09:12:11.336Z",
        "left_at": "2023-09-14T21:55:47.755Z",
        "created_at": "2023-09-15T08:36:48.424Z",
        "updated_at": "2023-09-15T01:37:50.162Z",
        "conference_id": "5080eeab-7aed-4c34-9233-aeb3ec99189c",
        "user_id": "user_entity_pk"
      }
    ],
    "roqUser": [
      {
        "reference": "0ff7db98-e6a0-4f4c-88ea-314612d346fb",
        "email": "Edna_Gibson3@gmail.com",
        "firstName": "Rodrick",
        "lastName": "Runolfsson",
        "active": true,
        "avatarUrl": "https://cloudflare-ipfs.com/ipfs/Qmd3W5DuhgHirLHGVixi6V76LhCkZUz6pnFt5AJBiyvHye/avatar/851.jpg",
        "tenantId": null
      },
      {
        "reference": "fb149a77-d93a-4ab4-9171-821703c933f9",
        "email": "Myah.Lebsack@yahoo.com",
        "firstName": "Justice",
        "lastName": "Reichert",
        "active": true,
        "avatarUrl": "https://cloudflare-ipfs.com/ipfs/Qmd3W5DuhgHirLHGVixi6V76LhCkZUz6pnFt5AJBiyvHye/avatar/822.jpg",
        "tenantId": null
      },
      {
        "reference": "d18c4e2e-597b-496d-9ed7-98b3da59cf83",
        "email": "Aidan_Satterfield@gmail.com",
        "firstName": "Jess",
        "lastName": "Willms",
        "active": true,
        "avatarUrl": "https://cloudflare-ipfs.com/ipfs/Qmd3W5DuhgHirLHGVixi6V76LhCkZUz6pnFt5AJBiyvHye/avatar/346.jpg",
        "tenantId": null
      },
      {
        "reference": "132c1af5-9dcc-40bb-b9e0-ed34861b0213",
        "email": "Jakayla69@yahoo.com",
        "firstName": "Cielo",
        "lastName": "Breitenberg-Wilderman",
        "active": true,
        "avatarUrl": "https://avatars.githubusercontent.com/u/53289164",
        "tenantId": null
      },
      {
        "reference": "3240d97d-efb1-4d91-974d-b0879ed0ee25",
        "email": "Asa73@hotmail.com",
        "firstName": "Keaton",
        "lastName": "Lesch",
        "active": true,
        "avatarUrl": "https://cloudflare-ipfs.com/ipfs/Qmd3W5DuhgHirLHGVixi6V76LhCkZUz6pnFt5AJBiyvHye/avatar/1149.jpg",
        "tenantId": null
      }
    ]
  },
  {
    "conference": [
      {
        "id": "917ac8a1-0524-45bf-b7dd-a2dd7bffcfba",
        "title": "International Conference on Technology",
        "start_time": "2023-09-15T03:39:45.549Z",
        "end_time": "2023-09-15T03:20:06.469Z",
        "created_at": "2023-09-14T23:18:22.895Z",
        "updated_at": "2023-09-14T22:54:30.891Z",
        "organization_id": "main_entity_pk"
      },
      {
        "id": "f8593d4c-83b7-4e42-b038-8a23c644e01a",
        "title": "Global Summit on Sustainable Development",
        "start_time": "2023-09-15T11:06:52.173Z",
        "end_time": "2023-09-14T21:34:07.474Z",
        "created_at": "2023-09-14T16:56:29.728Z",
        "updated_at": "2023-09-15T04:02:46.514Z",
        "organization_id": "main_entity_pk"
      },
      {
        "id": "8607493d-caec-4a44-8978-ec7d8dfa12b4",
        "title": "Annual Conference on Business Strategy",
        "start_time": "2023-09-15T01:37:58.851Z",
        "end_time": "2023-09-15T13:04:16.613Z",
        "created_at": "2023-09-15T01:45:19.278Z",
        "updated_at": "2023-09-14T16:09:42.555Z",
        "organization_id": "main_entity_pk"
      },
      {
        "id": "bcb043a8-06f7-4445-959e-1be48b402d93",
        "title": "Healthcare Innovation Forum",
        "start_time": "2023-09-15T07:14:59.803Z",
        "end_time": "2023-09-15T11:06:34.327Z",
        "created_at": "2023-09-15T05:49:20.865Z",
        "updated_at": "2023-09-15T01:57:07.386Z",
        "organization_id": "main_entity_pk"
      },
      {
        "id": "3cfd2bd4-4adc-420e-a34a-7eb7206102ab",
        "title": "Education Symposium on Future Trends",
        "start_time": "2023-09-14T23:25:34.578Z",
        "end_time": "2023-09-15T07:41:45.792Z",
        "created_at": "2023-09-15T02:39:05.740Z",
        "updated_at": "2023-09-14T22:30:02.508Z",
        "organization_id": "main_entity_pk"
      }
    ],
    "participant": [
      {
        "id": "7a7a0419-f9a6-449b-88c1-5d3baf4a025e",
        "joined_at": "2023-09-15T02:22:27.728Z",
        "left_at": "2023-09-15T06:46:40.393Z",
        "created_at": "2023-09-14T14:41:34.426Z",
        "updated_at": "2023-09-14T21:28:44.496Z",
        "conference_id": "bcb043a8-06f7-4445-959e-1be48b402d93",
        "user_id": "user_entity_pk"
      },
      {
        "id": "abd04d8a-7445-4403-9327-a9e201841c7e",
        "joined_at": "2023-09-15T03:17:40.089Z",
        "left_at": "2023-09-15T10:12:45.399Z",
        "created_at": "2023-09-15T13:09:04.517Z",
        "updated_at": "2023-09-15T00:36:48.335Z",
        "conference_id": "917ac8a1-0524-45bf-b7dd-a2dd7bffcfba",
        "user_id": "user_entity_pk"
      },
      {
        "id": "3fea2a50-0534-4c55-b1fd-d0027f33d0b2",
        "joined_at": "2023-09-15T01:01:17.847Z",
        "left_at": "2023-09-15T12:23:23.224Z",
        "created_at": "2023-09-15T13:54:26.657Z",
        "updated_at": "2023-09-14T22:38:22.275Z",
        "conference_id": "8607493d-caec-4a44-8978-ec7d8dfa12b4",
        "user_id": "user_entity_pk"
      },
      {
        "id": "8d3b84fa-f11b-4f34-be9b-c9177e979d69",
        "joined_at": "2023-09-15T12:56:16.841Z",
        "left_at": "2023-09-15T04:17:43.351Z",
        "created_at": "2023-09-15T13:46:58.152Z",
        "updated_at": "2023-09-15T02:31:42.197Z",
        "conference_id": "bcb043a8-06f7-4445-959e-1be48b402d93",
        "user_id": "user_entity_pk"
      },
      {
        "id": "87077f34-7268-4c4c-9650-91c98eed6379",
        "joined_at": "2023-09-15T05:19:04.174Z",
        "left_at": "2023-09-15T05:06:56.245Z",
        "created_at": "2023-09-15T10:39:29.659Z",
        "updated_at": "2023-09-15T01:41:10.818Z",
        "conference_id": "f8593d4c-83b7-4e42-b038-8a23c644e01a",
        "user_id": "user_entity_pk"
      }
    ],
    "roqUser": [
      {
        "reference": "3e145c90-d991-4f0a-b221-6bd2eb70f8e7",
        "email": "Maddison.Bergnaum@yahoo.com",
        "firstName": "Geovanni",
        "lastName": "Purdy",
        "active": true,
        "avatarUrl": "https://cloudflare-ipfs.com/ipfs/Qmd3W5DuhgHirLHGVixi6V76LhCkZUz6pnFt5AJBiyvHye/avatar/865.jpg",
        "tenantId": null
      },
      {
        "reference": "a69fb27b-60cf-4dc0-b68c-b09d27397d74",
        "email": "William_Stiedemann@hotmail.com",
        "firstName": "Alyson",
        "lastName": "Gleason",
        "active": true,
        "avatarUrl": "https://cloudflare-ipfs.com/ipfs/Qmd3W5DuhgHirLHGVixi6V76LhCkZUz6pnFt5AJBiyvHye/avatar/983.jpg",
        "tenantId": null
      },
      {
        "reference": "8b643a70-4cf2-4a9e-bc23-c2ba3cb08ea6",
        "email": "Arch.Tromp43@yahoo.com",
        "firstName": "Logan",
        "lastName": "Kuhn",
        "active": true,
        "avatarUrl": "https://cloudflare-ipfs.com/ipfs/Qmd3W5DuhgHirLHGVixi6V76LhCkZUz6pnFt5AJBiyvHye/avatar/545.jpg",
        "tenantId": null
      },
      {
        "reference": "5c2a915e-9f62-4c8b-bda5-ce8eefac9fa5",
        "email": "Maximillia_Ebert22@gmail.com",
        "firstName": "Sincere",
        "lastName": "Hilll-Monahan",
        "active": true,
        "avatarUrl": "https://avatars.githubusercontent.com/u/4347881",
        "tenantId": null
      },
      {
        "reference": "204b1f7b-bbab-4f6c-94a8-52d28e13e9c7",
        "email": "Nickolas.Heidenreich94@gmail.com",
        "firstName": "Jeramie",
        "lastName": "Veum",
        "active": true,
        "avatarUrl": "https://avatars.githubusercontent.com/u/62075597",
        "tenantId": null
      }
    ]
  },
  {
    "conference": [
      {
        "id": "6b686e77-9186-4dad-9df1-52e743226b16",
        "title": "International Summit on Innovation",
        "start_time": "2023-09-15T13:29:41.354Z",
        "end_time": "2023-09-15T13:20:45.729Z",
        "created_at": "2023-09-14T15:10:06.102Z",
        "updated_at": "2023-09-14T20:18:31.855Z",
        "organization_id": "main_entity_pk"
      },
      {
        "id": "47fea9d5-db64-4853-827c-09dbd91aa453",
        "title": "Global Conference on Sustainable Development",
        "start_time": "2023-09-15T08:35:46.021Z",
        "end_time": "2023-09-15T13:52:14.183Z",
        "created_at": "2023-09-14T17:23:52.624Z",
        "updated_at": "2023-09-15T02:48:55.028Z",
        "organization_id": "main_entity_pk"
      },
      {
        "id": "dd6aed00-8763-4231-b769-416b60190579",
        "title": "Annual Tech Expo",
        "start_time": "2023-09-15T03:59:45.992Z",
        "end_time": "2023-09-14T16:43:09.430Z",
        "created_at": "2023-09-15T02:58:24.720Z",
        "updated_at": "2023-09-15T13:55:37.009Z",
        "organization_id": "main_entity_pk"
      },
      {
        "id": "07e0b8ec-8aaa-412a-95af-8f43930a31d3",
        "title": "Healthcare Symposium",
        "start_time": "2023-09-15T00:08:28.791Z",
        "end_time": "2023-09-15T07:46:01.795Z",
        "created_at": "2023-09-15T10:34:01.305Z",
        "updated_at": "2023-09-14T16:38:06.989Z",
        "organization_id": "main_entity_pk"
      },
      {
        "id": "5a0b0e17-049e-455f-a2f6-0124b10e7ce6",
        "title": "Fashion Industry Forum",
        "start_time": "2023-09-14T17:14:13.315Z",
        "end_time": "2023-09-15T10:10:45.909Z",
        "created_at": "2023-09-15T14:09:50.139Z",
        "updated_at": "2023-09-14T14:52:52.416Z",
        "organization_id": "main_entity_pk"
      }
    ],
    "participant": [
      {
        "id": "98f2f678-f0c9-46b1-8e83-7e4637276556",
        "joined_at": "2023-09-15T13:36:58.215Z",
        "left_at": "2023-09-14T23:11:21.914Z",
        "created_at": "2023-09-15T12:23:59.169Z",
        "updated_at": "2023-09-14T15:20:58.827Z",
        "conference_id": "dd6aed00-8763-4231-b769-416b60190579",
        "user_id": "user_entity_pk"
      },
      {
        "id": "91097c40-3ea3-4d2c-9613-1f1900e80baa",
        "joined_at": "2023-09-15T03:56:31.506Z",
        "left_at": "2023-09-15T03:01:36.158Z",
        "created_at": "2023-09-14T16:40:21.175Z",
        "updated_at": "2023-09-14T18:00:05.747Z",
        "conference_id": "47fea9d5-db64-4853-827c-09dbd91aa453",
        "user_id": "user_entity_pk"
      },
      {
        "id": "4322daa4-668f-4f44-a475-3d3c54eae18c",
        "joined_at": "2023-09-14T15:18:50.293Z",
        "left_at": "2023-09-15T06:05:31.608Z",
        "created_at": "2023-09-15T02:38:28.568Z",
        "updated_at": "2023-09-15T05:24:40.280Z",
        "conference_id": "47fea9d5-db64-4853-827c-09dbd91aa453",
        "user_id": "user_entity_pk"
      },
      {
        "id": "52f66814-8be5-46f4-bffe-9508d5beaae4",
        "joined_at": "2023-09-15T02:34:35.834Z",
        "left_at": "2023-09-15T03:18:47.971Z",
        "created_at": "2023-09-14T18:41:09.284Z",
        "updated_at": "2023-09-14T21:09:05.553Z",
        "conference_id": "5a0b0e17-049e-455f-a2f6-0124b10e7ce6",
        "user_id": "user_entity_pk"
      },
      {
        "id": "7fc3c96d-5c03-4864-9e7f-0b96c96785e4",
        "joined_at": "2023-09-15T00:18:00.956Z",
        "left_at": "2023-09-14T20:33:44.400Z",
        "created_at": "2023-09-14T18:57:31.943Z",
        "updated_at": "2023-09-15T01:22:02.284Z",
        "conference_id": "dd6aed00-8763-4231-b769-416b60190579",
        "user_id": "user_entity_pk"
      }
    ],
    "roqUser": [
      {
        "reference": "4995b901-fa0e-4d80-9ec2-1e8f4f3834c8",
        "email": "Thaddeus_Little@hotmail.com",
        "firstName": "Jada",
        "lastName": "Bartell",
        "active": true,
        "avatarUrl": "https://avatars.githubusercontent.com/u/43986896",
        "tenantId": null
      },
      {
        "reference": "d1836ce9-3639-49de-bbb2-8428a9de2f28",
        "email": "Abelardo52@yahoo.com",
        "firstName": "Mary",
        "lastName": "Blick-Kiehn",
        "active": true,
        "avatarUrl": "https://cloudflare-ipfs.com/ipfs/Qmd3W5DuhgHirLHGVixi6V76LhCkZUz6pnFt5AJBiyvHye/avatar/587.jpg",
        "tenantId": null
      },
      {
        "reference": "d3a939c9-5606-4491-a222-283d9495ee8a",
        "email": "Unique_Vandervort2@hotmail.com",
        "firstName": "Robb",
        "lastName": "Mann",
        "active": true,
        "avatarUrl": "https://avatars.githubusercontent.com/u/42674076",
        "tenantId": null
      },
      {
        "reference": "be5d1b50-b4d0-4781-a1fe-ad72a0e44e63",
        "email": "Mario_Donnelly@yahoo.com",
        "firstName": "Enos",
        "lastName": "Batz",
        "active": true,
        "avatarUrl": "https://avatars.githubusercontent.com/u/18194488",
        "tenantId": null
      },
      {
        "reference": "2341fa62-a26d-4a78-a782-4f03ba9eb5da",
        "email": "Tom_Runolfsson@gmail.com",
        "firstName": "Trudie",
        "lastName": "O'Keefe",
        "active": true,
        "avatarUrl": "https://cloudflare-ipfs.com/ipfs/Qmd3W5DuhgHirLHGVixi6V76LhCkZUz6pnFt5AJBiyvHye/avatar/623.jpg",
        "tenantId": null
      }
    ]
  }
]
